forgi/whitelist.py
forgi/config.py
forgi/__init__.py
forgi/_k2n_standalone/knotted2nested.py
forgi/_k2n_standalone/output.py
forgi/_k2n_standalone/bpseq.py
forgi/_k2n_standalone/knots.py
forgi/_k2n_standalone/ct_simple.py
forgi/_k2n_standalone/rna2d.py
forgi/_k2n_standalone/__init__.py
forgi/_k2n_standalone/dict2d.py
forgi/graph/residue.py
forgi/graph/transform_graphs.py
forgi/graph/_basegraph.py
forgi/graph/_graph_construction.py
forgi/graph/sequence.py
forgi/graph/bulge_graph.py
forgi/graph/_cofold.py
forgi/graph/__init__.py
forgi/visual/mplotlib.py
forgi/visual/fornac.py
forgi/visual/__init__.py
forgi/utilities/graph.py
forgi/utilities/observedDict.py
forgi/utilities/debug.py
forgi/utilities/stuff.py
forgi/utilities/exceptions.py
forgi/utilities/numbered_dotbracket.py
forgi/utilities/containers.py
forgi/utilities/commandline_utils.py
forgi/utilities/__init__.py
forgi/projection/projection2d.py
forgi/projection/__init__.py
forgi/projection/hausdorff.py
forgi/threedee/__init__.py
forgi/threedee/model/linecloud.py
forgi/threedee/model/_ensemble.py
forgi/threedee/model/stats.py
forgi/threedee/model/transform_cg.py
forgi/threedee/model/similarity.py
forgi/threedee/model/coarse_grain.py
forgi/threedee/model/_ensemble2.py
forgi/threedee/model/descriptors.py
forgi/threedee/model/__init__.py
forgi/threedee/classification/aminor.py
forgi/threedee/classification/contact.py
forgi/threedee/classification/__init__.py
forgi/threedee/classification/_training/_parse_utils.py
forgi/threedee/classification/_training/aminor_training.py
forgi/threedee/classification/_training/train_aminor.py
forgi/threedee/classification/_training/__init__.py
forgi/threedee/visual/pymol.py
forgi/threedee/visual/__init__.py
forgi/threedee/utilities/virtual_residues.py
forgi/threedee/utilities/mcannotate.py
forgi/threedee/utilities/vector.py
forgi/threedee/utilities/pdb.py
forgi/threedee/utilities/cytvec.cpython-37m-x86_64-linux-gnu.so
forgi-2.2.3.dist-info/METADATA
forgi-2.2.3.dist-info/CREDITS
forgi-2.2.3.dist-info/RECORD
forgi-2.2.3.dist-info/LICENSE
forgi-2.2.3.dist-info/top_level.txt
forgi-2.2.3.dist-info/WHEEL
